<?xml version="1.0" encoding="utf-8"?>
<resources>
    <string name="app_name">Dogecoin Wallet</string>
    <string name="app_name_short">Dogecoin</string>

    <string-array name="preferences_block_explorer_values">
        <item>https://sochain.com/%s/DOGE/</item>
        <item>https://live.blockcypher.com/doge/%s/</item>
    </string-array>
    <string-array name="preferences_block_explorer_labels">
        <item>SoChain</item>
        <item>BlockCypher</item>
    </string-array>

    <string name="preferences_battery_optimization_title">Battery optimization</string>
    <string name="preferences_battery_optimization_summary">Prevent Android from putting the app to sleep during synchronization.</string>
    
    <!-- Total Nodes -->
    <string name="total_nodes_title">Total Nodes</string>
    <string name="total_nodes_count">%d Nodes Worldwide</string>
    <string name="last_updated">Last updated: %s</string>
    <string name="refresh">Refresh</string>
    <string name="discovered_nodes">Discovered Nodes</string>
</resources>
